json2q-0.3.0.dist-info/METADATA
json2q-0.3.0.dist-info/WHEEL
json2q-0.3.0.dist-info/entry_points.txt
json2q-0.3.0.dist-info/licenses/LICENSE.TXT
json2q/__init__.py
json2q/json2q.py
json2q-0.3.0.dist-info/RECORD
