Metadata-Version: 2.1
Name: json2q
Version: 0.3.0
Summary: Convert JSON filters to Q expression
Author-Email: Cook Ding Developers <developer@cookding.com>
License: MIT
Requires-Python: >=3.12
